quarto_graft/__init__.py
quarto_graft/branches.py
quarto_graft/build.py
quarto_graft/cli.py
quarto_graft/constants.py
quarto_graft/file_utils.py
quarto_graft/git_utils.py
quarto_graft/graft-templates/README.md
quarto_graft/graft-templates/markdown/.gitignore
quarto_graft/graft-templates/markdown/Makefile
quarto_graft/graft-templates/markdown/README.md
quarto_graft/graft-templates/markdown/_quarto.yaml
quarto_graft/graft-templates/markdown/docs/.gitignore
quarto_graft/graft-templates/markdown/docs/index.qmd
quarto_graft/graft-templates/py-jupyter/.gitignore
quarto_graft/graft-templates/py-jupyter/Makefile
quarto_graft/graft-templates/py-jupyter/README.md
quarto_graft/graft-templates/py-jupyter/_quarto.yaml
quarto_graft/graft-templates/py-jupyter/docs/.gitignore
quarto_graft/graft-templates/py-jupyter/docs/index.qmd
quarto_graft/graft-templates/py-jupyter/docs/notebook.ipynb
quarto_graft/graft-templates/py-jupyter/pyproject.toml
quarto_graft/graft-templates/py-jupyter/src/{{ package_name }}/__init__.py
quarto_graft/graft-templates/py-jupyter/src/{{ package_name }}/sample.py
quarto_graft/graft-templates/py-marimo/.gitignore
quarto_graft/graft-templates/py-marimo/Makefile
quarto_graft/graft-templates/py-marimo/README.md
quarto_graft/graft-templates/py-marimo/TRUNK_INSTRUCTIONS.md
quarto_graft/graft-templates/py-marimo/_extensions/marimo-team/marimo/_extension.yml
quarto_graft/graft-templates/py-marimo/_extensions/marimo-team/marimo/command.py
quarto_graft/graft-templates/py-marimo/_extensions/marimo-team/marimo/extract.py
quarto_graft/graft-templates/py-marimo/_extensions/marimo-team/marimo/marimo-execute.lua
quarto_graft/graft-templates/py-marimo/_extensions/marimo-team/marimo/utils.lua
quarto_graft/graft-templates/py-marimo/_extensions/quarto-ext/fontawesome/_extension.yml
quarto_graft/graft-templates/py-marimo/_extensions/quarto-ext/fontawesome/assets/LICENSE.txt
quarto_graft/graft-templates/py-marimo/_extensions/quarto-ext/fontawesome/assets/css/all.css
quarto_graft-0.0.22.dist-info/WHEEL
quarto_graft-0.0.22.dist-info/entry_points.txt
quarto_graft-0.0.22.dist-info/METADATA
quarto_graft-0.0.22.dist-info/RECORD
