Metadata-Version: 2.3
Name: quarto-graft
Version: 0.0.22
Summary: Quarto GitHub Pages branch graft tool
Requires-Dist: jinja2>=3.1
Requires-Dist: packaging>=25.0
Requires-Dist: pygit2>=1.19.0
Requires-Dist: quarto-cli>=1.8.26
Requires-Dist: questionary>=2.1.1
Requires-Dist: ruamel-yaml>=0.18.16
Requires-Dist: ruff>=0.14.10
Requires-Dist: typer>=0.20.1
Requires-Python: >=3.11
